unidic2ud/__init__.py
unidic2ud/__main__.py
unidic2ud/cli.py
unidic2ud/conllusvgview.js
unidic2ud/deprelja.py
unidic2ud/unidic2ud.py
unidic2ud/cabocha/__init__.py
unidic2ud/cabocha/cli.py
unidic2ud/cabocha/unidic2cabocha.py
unidic2ud/download/ipadic/char.bin
unidic2ud/download/ipadic/dicrc
unidic2ud/download/ipadic/matrix.bin
unidic2ud/download/ipadic/sys.dic
unidic2ud/download/ipadic/unk.dic
unidic2ud/spacy/__init__.py
unidic2ud/spacy/unidic2spacy.py
unidic2ud-1.6.0.dist-info/LICENSE.txt
unidic2ud-1.6.0.dist-info/METADATA
unidic2ud-1.6.0.dist-info/WHEEL
unidic2ud-1.6.0.dist-info/entry_points.txt
unidic2ud-1.6.0.dist-info/top_level.txt
unidic2ud-1.6.0.dist-info/RECORD
