Metadata-Version: 2.1
Name: unidic2ud
Version: 1.6.0
Summary: Tokenizer POS-tagger Lemmatizer and Dependency-parser for modern and contemporary Japanese
Home-page: https://github.com/KoichiYasuoka/UniDic2UD
Author: Koichi Yasuoka
Author-email: yasuoka@kanji.zinbun.kyoto-u.ac.jp
License: MIT
Project-URL: ud-ja-kanbun, https://corpus.kanji.zinbun.kyoto-u.ac.jp/gitlab/Kanbun/ud-ja-kanbun
Project-URL: Source, https://github.com/KoichiYasuoka/UniDic2UD
Project-URL: Tracker, https://github.com/KoichiYasuoka/UniDic2UD/issues
Keywords: unidic udpipe mecab nlp
Platform: UNKNOWN
Classifier: License :: OSI Approved :: MIT License
Classifier: Programming Language :: Python :: 3
Classifier: Operating System :: OS Independent
Classifier: Topic :: Text Processing :: Linguistic
Classifier: Natural Language :: Japanese
Requires-Python: >=3.6
Requires-Dist: ufal.udpipe (>=1.2.0)
Requires-Dist: mecab-python3 (>=0.996)
Requires-Dist: pip (>=10.0.1)
